uc3m_pic/__init__.py
uc3m_pic/eval.py
uc3m_pic/utils.py
uc3m_pic-0.4.0.dist-info/licenses/LICENSE
uc3m_pic-0.4.0.dist-info/METADATA
uc3m_pic-0.4.0.dist-info/WHEEL
uc3m_pic-0.4.0.dist-info/top_level.txt
uc3m_pic-0.4.0.dist-info/RECORD
